qbc_dsbm/__init__.py
qbc_dsbm/__main__.py
qbc_dsbm/args.py
qbc_dsbm/bigraph.py
qbc_dsbm/cli.py
qbc_dsbm/io_config.py
qbc_dsbm/loggers.py
qbc_dsbm/logging.py
qbc_dsbm/py.typed
qbc_dsbm/solve_problems.py
qbc_dsbm/strategies.py
qbc_dsbm/binary_matrix/__init__.py
qbc_dsbm/binary_matrix/configs.py
qbc_dsbm/binary_matrix/create.py
qbc_dsbm/binary_matrix/items.py
qbc_dsbm/binary_matrix/ops.py
qbc_dsbm/binary_matrix/views.py
qbc_dsbm/binary_matrix/apps/__init__.py
qbc_dsbm/binary_matrix/apps/create.py
qbc_dsbm/binary_matrix/apps/ops.py
qbc_dsbm/binary_matrix/apps/views.py
qbc_dsbm/models/__init__.py
qbc_dsbm/models/exact_dsbm.py
qbc_dsbm/models/heuristic_dsbm.py
qbc_dsbm/models/konig.py
qbc_dsbm/models/solvers.py
qbc_dsbm/models/views.py
qbc_dsbm-0.5.0.dist-info/LICENCE
qbc_dsbm-0.5.0.dist-info/METADATA
qbc_dsbm-0.5.0.dist-info/WHEEL
qbc_dsbm-0.5.0.dist-info/entry_points.txt
qbc_dsbm-0.5.0.dist-info/top_level.txt
qbc_dsbm-0.5.0.dist-info/RECORD
