Metadata-Version: 2.1
Name: qbc_dsbm
Version: 0.5.0
Summary: Codes for quasibiclique
Author-email: vepain <victorepain@disroot.org>, randonov <rumen.andonov@irisa.fr>
License: ### GNU GENERAL PUBLIC LICENSE
Requires-Python: >=3.10
License-File: LICENCE
Requires-Dist: pulp<2.10,>=2.9
Requires-Dist: pandas<2.3,>=2.2
Requires-Dist: numpy<2.2,>=2.1
Requires-Dist: PyYAML<6.1,>=6.0
Requires-Dist: gurobipy<11.1,>=11.0
Requires-Dist: typer<0.13,>=0.12
Requires-Dist: scikit-learn<1.6,>=1.5
